LinguaLab/__init__.py
LinguaLab/text_translations.py
LinguaLab/transcribe_video_files.py
lingualab-3.5.10.dist-info/licenses/LICENSE
lingualab-3.5.10.dist-info/METADATA
lingualab-3.5.10.dist-info/WHEEL
lingualab-3.5.10.dist-info/top_level.txt
lingualab-3.5.10.dist-info/RECORD
