Metadata-Version: 2.4
Name: LinguaLab
Version: 3.5.10
Summary: A multilingual text and voice processing toolkit
Author-email: Jon Ander Gabantxo <jagabantxo@gmail.com>
License: MIT License
Project-URL: Homepage, https://github.com/EusDancerDev/LinguaLab
Project-URL: Documentation, https://github.com/EusDancerDev/LinguaLab#readme
Project-URL: Repository, https://github.com/EusDancerDev/LinguaLab.git
Project-URL: Bug Reports, https://github.com/EusDancerDev/LinguaLab/issues
Keywords: language processing,translation,speech recognition,text processing
Classifier: Development Status :: 4 - Beta
Classifier: Intended Audience :: Developers
Classifier: Topic :: Text Processing
Classifier: Topic :: Text Processing :: Linguistic
Classifier: Topic :: Software Development :: Libraries :: Python Modules
Classifier: Programming Language :: Python :: 3
Classifier: Programming Language :: Python :: 3.10
Classifier: Programming Language :: Python :: 3.11
Classifier: Programming Language :: Python :: 3.12
Classifier: Operating System :: OS Independent
Requires-Python: >=3.10
License-File: LICENSE
Requires-Dist: numpy>=1.21.0
Requires-Dist: pandas>=1.3.0
Requires-Dist: filewise>=3.11.6
Requires-Dist: pygenutils>=16.3.0
Requires-Dist: paramlib>=3.4.10
Requires-Dist: SpeechRecognition>=3.10.0
Requires-Dist: googletrans>=4.0.0
Requires-Dist: gTTS>=2.3.0
Provides-Extra: dev
Requires-Dist: pytest>=7.0.0; extra == "dev"
Requires-Dist: pytest-cov>=4.0.0; extra == "dev"
Requires-Dist: black>=22.0.0; extra == "dev"
Requires-Dist: flake8>=5.0.0; extra == "dev"
Dynamic: license-file
